model_align/__init__.py
model_align/util.py
model_align/torch2paddle/__init__.py
model_align/torch2paddle/convert_layer/__init__.py
model_align/torch2paddle/convert_layer/convert_bn.py
model_align/torch2paddle/convert_layer/convert_conv.py
model_align/torch2paddle/convert_layer/convert_linear.py
model_align/torch2paddle/convert_layer/convert_ln.py
model_align/torch2paddle/convert_layer/util.py
model_align-1.0.dist-info/METADATA
model_align-1.0.dist-info/WHEEL
model_align-1.0.dist-info/top_level.txt
model_align-1.0.dist-info/RECORD
